waddle/__init__.py
waddle/server.py
waddle/waddle.py
waddleml-0.1.3.data/scripts/waddle
waddleml-0.1.3.dist-info/LICENSE
waddleml-0.1.3.dist-info/METADATA
waddleml-0.1.3.dist-info/WHEEL
waddleml-0.1.3.dist-info/top_level.txt
waddleml-0.1.3.dist-info/RECORD
