Metadata-Version: 2.1
Name: waddleml
Version: 0.1.3
Summary: WaddleML is a machine learning stats tracker built on DuckDB
Author: Brian Guarraci
License: MIT
Classifier: Programming Language :: Python :: 3
Classifier: License :: OSI Approved :: MIT License
Requires-Python: <=3.12,>=3.8
License-File: LICENSE
Requires-Dist: duckdb==1.1.0
Requires-Dist: fastapi==0.114.2
Requires-Dist: psutil==6.0.0
Requires-Dist: pynvml==11.5.3
Requires-Dist: requests==2.32.3
Requires-Dist: rich==13.8.1
Requires-Dist: uvicorn==0.30.6
Requires-Dist: websockets==13.0.1
